hidapi_py/__init__.py
hidapi_py/hidapi_py.cpython-311-i386-linux-musl.so
hidapi_py/hidapi_py.pyi
hidapi_py.libs/libgcc_s-887de51c.so.1
hidapi_py.libs/libhidapi-hidraw-73418cf8.so.0.14.0
hidapi_py.libs/libstdc++-d6415257.so.6.0.33
hidapi_py.libs/libudev-d51dfeb0.so.1.6.3
hidapi_py-0.1.2.dist-info/METADATA
hidapi_py-0.1.2.dist-info/WHEEL
hidapi_py-0.1.2.dist-info/RECORD
hidapi_py-0.1.2.dist-info/licenses/LICENSE.txt
